main.py
commands/__init__.py
commands/init.py
core/__init__.py
core/__version__.py
core/config_reader.py
core/project_generator.py
core/version.py
core/decorators/__init__.py
core/decorators/generator.py
core/generators/__init__.py
core/generators/alembic.py
core/generators/orchestrator.py
core/generators/structure.py
core/generators/configs/__init__.py
core/generators/configs/base.py
core/generators/configs/celery.py
core/generators/configs/env.py
core/generators/configs/gitignore.py
core/generators/configs/license.py
core/generators/configs/pyproject.py
core/generators/configs/readme.py
core/generators/configs/redis.py
core/generators/deployment/__init__.py
core/generators/deployment/base.py
core/generators/deployment/docker_compose.py
core/generators/deployment/dockerfile.py
core/generators/deployment/dockerignore.py
core/generators/templates/__init__.py
core/generators/templates/base.py
core/generators/templates/app/__init__.py
core/generators/templates/app/app.py
core/generators/templates/app/base.py
core/generators/templates/app/celery.py
core/generators/templates/app/cors.py
core/generators/templates/app/database.py
core/generators/templates/app/deps.py
core/generators/templates/app/email.py
core/generators/templates/app/jwt.py
core/generators/templates/app/logger_config.py
core/generators/templates/app/logger_manager.py
core/generators/templates/app/main.py
core/generators/templates/app/redis.py
core/generators/templates/app/security.py
core/generators/templates/app/settings.py
core/generators/templates/crud/__init__.py
core/generators/templates/crud/token.py
core/generators/templates/crud/user.py
core/generators/templates/database/__init__.py
core/generators/templates/database/connection.py
core/generators/templates/database/dependencies.py
core/generators/templates/database/mysql.py
core/generators/templates/database/postgresql.py
core/generators/templates/database/sqlite.py
core/generators/templates/decorators/rate_limit.py
ningfastforge-0.1.8.5.dist-info/licenses/LICENSE
ningfastforge-0.1.8.5.dist-info/METADATA
ningfastforge-0.1.8.5.dist-info/WHEEL
ningfastforge-0.1.8.5.dist-info/entry_points.txt
ningfastforge-0.1.8.5.dist-info/top_level.txt
ningfastforge-0.1.8.5.dist-info/RECORD
