Metadata-Version: 2.4
Name: ningfastforge
Version: 0.1.8.5
Summary: A modern FastAPI project scaffolding CLI tool
Author-email: ning3739 <ln729500172@gmail.com>
Maintainer-email: ning3739 <ln729500172@gmail.com>
License: MIT
Project-URL: Homepage, https://ningfastforge.readthedocs.io/
Project-URL: Documentation, https://ningfastforge.readthedocs.io/
Project-URL: Repository, https://github.com/ning3739/forge
Project-URL: Issues, https://github.com/ning3739/forge/issues
Project-URL: Changelog, https://github.com/ning3739/forge/blob/main/CHANGELOG.md
Keywords: fastapi,cli,scaffolding,generator,template
Classifier: Development Status :: 3 - Alpha
Classifier: Intended Audience :: Developers
Classifier: License :: OSI Approved :: MIT License
Classifier: Programming Language :: Python :: 3
Classifier: Programming Language :: Python :: 3.9
Classifier: Programming Language :: Python :: 3.10
Classifier: Programming Language :: Python :: 3.11
Classifier: Programming Language :: Python :: 3.12
Classifier: Programming Language :: Python :: 3.13
Classifier: Topic :: Software Development :: Code Generators
Classifier: Topic :: Software Development :: Libraries :: Application Frameworks
Requires-Python: >=3.9
License-File: LICENSE
Requires-Dist: typer>=0.21.0
Requires-Dist: rich>=14.0.0
Requires-Dist: questionary>=1.10.0
Requires-Dist: packaging>=21.0
Provides-Extra: dev
Requires-Dist: pytest>=8.0.0; extra == "dev"
Requires-Dist: pytest-cov>=4.0.0; extra == "dev"
Dynamic: license-file
